odoo/addons/partner_default_sale_discount/README.rst
odoo/addons/partner_default_sale_discount/__init__.py
odoo/addons/partner_default_sale_discount/__manifest__.py
odoo/addons/partner_default_sale_discount/i18n/am.po
odoo/addons/partner_default_sale_discount/i18n/ar.po
odoo/addons/partner_default_sale_discount/i18n/bg.po
odoo/addons/partner_default_sale_discount/i18n/bs.po
odoo/addons/partner_default_sale_discount/i18n/ca.po
odoo/addons/partner_default_sale_discount/i18n/cs.po
odoo/addons/partner_default_sale_discount/i18n/da.po
odoo/addons/partner_default_sale_discount/i18n/de.po
odoo/addons/partner_default_sale_discount/i18n/el_GR.po
odoo/addons/partner_default_sale_discount/i18n/en_GB.po
odoo/addons/partner_default_sale_discount/i18n/es.po
odoo/addons/partner_default_sale_discount/i18n/es_CR.po
odoo/addons/partner_default_sale_discount/i18n/es_EC.po
odoo/addons/partner_default_sale_discount/i18n/es_ES.po
odoo/addons/partner_default_sale_discount/i18n/es_MX.po
odoo/addons/partner_default_sale_discount/i18n/es_VE.po
odoo/addons/partner_default_sale_discount/i18n/et.po
odoo/addons/partner_default_sale_discount/i18n/fi.po
odoo/addons/partner_default_sale_discount/i18n/fr.po
odoo/addons/partner_default_sale_discount/i18n/fr_CA.po
odoo/addons/partner_default_sale_discount/i18n/fr_CH.po
odoo/addons/partner_default_sale_discount/i18n/gl.po
odoo/addons/partner_default_sale_discount/i18n/hr.po
odoo/addons/partner_default_sale_discount/i18n/hr_HR.po
odoo/addons/partner_default_sale_discount/i18n/hu.po
odoo/addons/partner_default_sale_discount/i18n/it.po
odoo/addons/partner_default_sale_discount/i18n/ja.po
odoo/addons/partner_default_sale_discount/i18n/lt.po
odoo/addons/partner_default_sale_discount/i18n/lv.po
odoo/addons/partner_default_sale_discount/i18n/mk.po
odoo/addons/partner_default_sale_discount/i18n/mn.po
odoo/addons/partner_default_sale_discount/i18n/nb.po
odoo/addons/partner_default_sale_discount/i18n/nb_NO.po
odoo/addons/partner_default_sale_discount/i18n/nl.po
odoo12_addon_partner_default_sale_discount-12.0.1.0.1.dist-info/METADATA
odoo12_addon_partner_default_sale_discount-12.0.1.0.1.dist-info/WHEEL
odoo12_addon_partner_default_sale_discount-12.0.1.0.1.dist-info/top_level.txt
odoo12_addon_partner_default_sale_discount-12.0.1.0.1.dist-info/RECORD
